intune_study/__init__.py
intune_study/app_management.py
intune_study/create_compliance.py
intune_study/device_management.py
intune_study/manage.py
intune_study-0.0.5.dist-info/METADATA
intune_study-0.0.5.dist-info/WHEEL
intune_study-0.0.5.dist-info/top_level.txt
intune_study-0.0.5.dist-info/RECORD
