Metadata-Version: 2.1
Name: intune-study
Version: 0.0.5
Summary: A Python package for managing device compliance policies in Intune using Microsoft Graph API
Author: Shiyas Shaji
Author-email: shiyasshaji1999@gmail.com
Classifier: Programming Language :: Python :: 3
Classifier: License :: OSI Approved :: MIT License
Classifier: Operating System :: OS Independent
Requires-Python: >=3.6
Requires-Dist: requests
Requires-Dist: python-dotenv
